pysnp-0.2.4.dist-info/licenses/LICENSE
snp/__init__.py
snp/core.py
snp/examples.py
pysnp-0.2.4.dist-info/METADATA
pysnp-0.2.4.dist-info/WHEEL
pysnp-0.2.4.dist-info/top_level.txt
pysnp-0.2.4.dist-info/RECORD
