Metadata-Version: 2.4
Name: pysnp
Version: 0.2.4
Summary: Stepwise Noise Peeling (SNP) for Nadaraya–Watson Regression
Home-page: https://github.com/bistoonh/SNP-Python
Author: Bistoon Hosseini
Author-email: bistoon.hosseini@gmail.com
License: MIT License
Requires-Python: >=3.7
License-File: LICENSE
Requires-Dist: numpy>=1.21
Dynamic: author-email
Dynamic: home-page
Dynamic: license-file
Dynamic: requires-python
